mehdi/__init__.py
mehdi/havij.py
mehdi-0.23.dist-info/METADATA
mehdi-0.23.dist-info/WHEEL
mehdi-0.23.dist-info/top_level.txt
mehdi-0.23.dist-info/RECORD
