Metadata-Version: 2.1
Name: mehdi
Version: 0.23
Summary: Stacrypt utility package
Home-page: UNKNOWN
Author: Stacrypt
Author-email: Stacrypt@info.com
License: UNKNOWN
Platform: UNKNOWN
Classifier: Programming Language :: Python :: 3
Classifier: License :: OSI Approved :: MIT License
Classifier: Operating System :: OS Independent
Requires-Python: >=3.7
